cdk8s_plus_17/__init__.py
cdk8s_plus_17/py.typed
cdk8s_plus_17/_jsii/__init__.py
cdk8s_plus_17/_jsii/cdk8s-plus-17@0.33.0.jsii.tgz
cdk8s_plus_17-0.33.0.dist-info/METADATA
cdk8s_plus_17-0.33.0.dist-info/WHEEL
cdk8s_plus_17-0.33.0.dist-info/top_level.txt
cdk8s_plus_17-0.33.0.dist-info/RECORD
