Metadata-Version: 2.1
Name: cdk8s-plus-17
Version: 0.33.0
Summary: High level abstractions on top of cdk8s
Home-page: https://github.com/awslabs/cdk8s.git
Author: Amazon Web Services
License: Apache-2.0
Project-URL: Source, https://github.com/awslabs/cdk8s.git
Platform: UNKNOWN
Classifier: Intended Audience :: Developers
Classifier: Operating System :: OS Independent
Classifier: Programming Language :: JavaScript
Classifier: Programming Language :: Python :: 3 :: Only
Classifier: Programming Language :: Python :: 3.6
Classifier: Programming Language :: Python :: 3.7
Classifier: Programming Language :: Python :: 3.8
Classifier: Typing :: Typed
Classifier: Development Status :: 4 - Beta
Classifier: License :: OSI Approved
Requires-Python: >=3.6
Requires-Dist: cdk8s (<0.34.0,>=0.33.0)
Requires-Dist: constructs (<4.0.0,>=3.0.4)
Requires-Dist: jsii (<2.0.0,>=1.13.0)
Requires-Dist: publication (>=0.0.3)
